plone.theme-4.0.4-py3.13-nspkg.pth
plone/theme/README.rst
plone/theme/__init__.py
plone/theme/configure.zcml
plone/theme/interfaces.py
plone/theme/layer.py
plone/theme/testing.py
plone/theme/tests/__init__.py
plone/theme/tests/default.pt
plone/theme/tests/interfaces.py
plone/theme/tests/mytheme.pt
plone/theme/tests/testBrowserLayerPrecedence.py
plone/theme/tests/test_doctest.py
plone/theme/tests/tests.zcml
plone_theme-4.0.4.dist-info/METADATA
plone_theme-4.0.4.dist-info/WHEEL
plone_theme-4.0.4.dist-info/namespace_packages.txt
plone_theme-4.0.4.dist-info/top_level.txt
plone_theme-4.0.4.dist-info/RECORD
